kwikd/__init__.py
kwikd/_internal/__init__.py
kwikd/cli/__init__.py
kwikd-0.0.1.dist-info/LICENSE
kwikd-0.0.1.dist-info/METADATA
kwikd-0.0.1.dist-info/WHEEL
kwikd-0.0.1.dist-info/entry_points.txt
kwikd-0.0.1.dist-info/top_level.txt
kwikd-0.0.1.dist-info/RECORD
