Metadata-Version: 2.1
Name: kwikd
Version: 0.0.1
Summary: kwik framework development tools
Home-page: https://github.com/sroedger/kwikd
Author: Sam Roedger
Author-email: sroedger@gmail.com
License: MIT
Keywords: kwik,kwikd,framework,kwik framework,web,devtools,development tools,web development,services,microservices
Platform: UNKNOWN
Classifier: Development Status :: 1 - Planning
Classifier: License :: OSI Approved :: MIT License
Classifier: Operating System :: OS Independent
Classifier: Environment :: Web Environment
Classifier: Intended Audience :: Developers
Classifier: Programming Language :: Python
Classifier: Programming Language :: Python :: 3
Classifier: Programming Language :: Python :: 3 :: Only
Classifier: Programming Language :: Python :: 3.7
Classifier: Programming Language :: Python :: 3.8
Classifier: Programming Language :: Python :: 3.9
Classifier: Topic :: Internet :: WWW/HTTP
Classifier: Topic :: Software Development :: Libraries :: Application Frameworks
Requires-Python: >=3.7
License-File: LICENSE
